{
  "현대건설올해만서울정비사업장4곳공사비증액요청인상행진": "2026-04-03",
  "단독압구정4구역접은현대건설넥스트압구정으로목동찍었다": "2026-04-03",
  "포스코이앤씨방배15구역정비사업계약조건변경논란조합과갈등": "2026-04-03",
  "GS건설봉천제14구역재개발정비사업공사수주계약체결": "2026-04-03",
  "이란전쟁충격파동남아핵무장가속험로예고": "2026-04-03",
  "전세계에너지초비상석탄늘리고재생에너지전환에속도": "2026-04-03",
  "저유가시대뒤안길로에너지질서흔드는4가지변수": "2026-04-03",
  "중동발원자재수급난에건설현장초비상": "2026-04-03",
  "매물잠금시작됐나서울집값상승폭확대성북강서1분기3": "2026-04-03",
  "현대건설마천4구역공사비6733억으로증액요청75인상": "2026-04-03",
  "DL이앤씨상대원2구역재개발서쫓겨날위기아크로갈등뭐길래": "2026-04-03",
  "현대건설수주잔고95조최대포스코이앤씨일감7년치확보": "2026-04-03",
  "대우건설글로벌인프라본부신설한승해외사업단장첫본부장내정": "2026-04-03",
  "포스코이앤씨영업정지우려속정비사업물꼬틀까": "2026-04-03",
  "대우건설원전해외사업통합글로벌인프라본부신설시장확대": "2026-04-03",
  "대우건설원전축으로사업재편글로벌수주경쟁력강화": "2026-04-03",
  "대우건설글로벌인프라본부신설해원전사업확장조직개편단행": "2026-04-03",
  "현대건설대조등촌이어마천4구역에공사비올려달라": "2026-04-03",
  "현대건설마천4구역공사비2천899억원증액요청": "2026-04-03",
  "중동발건설원가쇼크공사비인상둘러싼분쟁불가피": "2026-04-03",
  "단독성수4지구6일대우건설입찰보증금반환1400만원차감": "2026-04-03",
  "대우건설도시정비연간목표36채웠지만성수4재입찰변수에추가": "2026-04-03",
  "건설Pick대우건설현대건설삼표미래동력확보와사회공헌활동": "2026-04-03",
  "실적반등신호탄현대대우GS건설불황에도개발용지늘려": "2026-04-03",
  "SK이터닉스신안앞바다에해상풍력띄운다에너지대전환가속": "2026-04-03",
  "대우건설글로벌원전공략속도글로벌인프라본부신설": "2026-04-03",
  "SMR미국전력인프라선점DL이앤씨에너지EPC플레이어로체질": "2026-04-03",
  "중동공사비인상우려커진다국토부비상TF운영": "2026-04-03",
  "중동발자재값상승건설업계공사비인상명분형성": "2026-04-03",
  "국토부건설현장비상경제TF가동중동전쟁발자재수급난정조준": "2026-04-03",
  "7조압구정35구역수주본격화현대건설브랜드계승승부수": "2026-04-04",
  "대우건설롯데건설현대건설1분기정비사업1조클럽달성": "2026-04-04",
  "분양브리프현대건설DL이앤씨GS건설IPARK현대산업개발": "2026-04-04",
  "C워드DL이앤씨호반건설대우건설KCC": "2026-04-04",
  "증권뉴스브리핑대법정영채전NH대표중징계취소불장에10대증": "2026-04-04",
  "에너지슈퍼트릴레마한국생존전략은": "2026-04-04",
  "에너지동맹맺었다원전핵연료부터해상풍력까지전방위": "2026-04-04",
  "중동전쟁장기화대응국토부건설현장비상경제TF격상운영": "2026-04-04",
  "전쟁공사비인상도미노건설사마천4구역에75올려달라": "2026-04-04",
  "건설원자재가격줄줄이인상공사비증액현실로": "2026-04-04",
  "단독상대원2구역조합장이사2인해임GS건설입성제동": "2026-04-04",
  "KB증권4월첫째주현대건설등16종목매수추천": "2026-04-04",
  "삼성물산반포푸르지오리모델링우선협상대상자선정": "2026-04-04",
  "대우건설의협력의가치가격에서안전으로": "2026-04-04",
  "에너지리스크속기회윤석천2차전지ESS구조적성장지속경제": "2026-04-04",
  "인도한국조선해양강국향한해양동맹결성KOICA와실행계획": "2026-04-04",
  "고리2호기재가동돌입계속운전정책의선두사례될까": "2026-04-04",
  "패트롤경기도양주시연천군의정부시포천시": "2026-04-04",
  "중동쇼크자재난공사비갈등에공급경고등국토부차관급TF가": "2026-04-04",
  "이란미사일한방에멈췄다글로벌알루미늄대란오나": "2026-04-04",
  "롯데건설도시정비부동산개발장밋빛오일근취임첫해순풍에돛": "2026-04-05",
  "포스코이앤씨1분기도시정비몸풀기송치영반포목동에서격전벼른": "2026-04-05",
  "대우건설2026우수협력회사동반성장간담회개최": "2026-04-05",
  "성수4지구재입찰돌입대우참여불투명롯데적극참여": "2026-04-05",
  "현대건설뉴에너지작년매출예상치넘겼다수익성확대가속": "2026-04-05",
  "MS사장이란전쟁이후데이터센터보안패러다임바꿔야물리적": "2026-04-05",
  "대우건설원전확대대비조직개편글로벌인프라본부신설": "2026-04-05",
  "비즈토크전쟁에자재비오르자건설사공사비인상각오하세요": "2026-04-05",
  "페인트값50폭등건설업계공사멈출수도있다": "2026-04-05",
  "새집들어갈날기다렸는데요즘현장분위기심상치않다이슬기의": "2026-04-05",
  "대우건설2026우수협력회사동반성장간담회개최안전상생": "2026-04-05",
  "GS건설SK에코플랜트노량진라클라체자이드파인분양시작": "2026-04-05",
  "치솟는공사비에PM찾는대형정비사업장들시간이곧돈": "2026-04-05",
  "단독분양가더받자강남3구용산구후분양절반": "2026-04-05",
  "사설재생에너지확대위해개발이익공유제확립을": "2026-04-05",
  "대우건설원전확대대응조직개편글로벌인프라본부신설": "2026-04-05",
  "대우건설원전사업경쟁력높인다": "2026-04-05",
  "중동자재쇼크현실화국내건설현장도비상등": "2026-04-05",
  "이번주관심주이란전쟁이오히려기회삼성EA전후복구기대": "2026-04-05",
  "부동산PF부실185조원정리중동리스크변수주시": "2026-04-05",
  "현대건설디에이치아파트서겪은황당한경험이름값좀했으면": "2026-04-06",
  "코스피코스닥클로봇HD현대중공업대우건설에스트래픽SKC클로": "2026-04-06",
  "중동전쟁치솟는공사비에자재수급불안까지정비사업갈등확": "2026-04-06",
  "단독자잿값20인상건설현장중동청구서미이란전쟁": "2026-04-06",
  "시각과전망김진만신규원전후보지선정객관적공정해야하는이": "2026-04-06",
  "단독혁신금융덕에에너지안보해상풍력특수선박뜬다": "2026-04-06",
  "탄소감축공론화위시민대표단미래세대재생에너지전환시점예산": "2026-04-06",
  "중동발나프타쇼크건설현장비상공사비갈등도미노우려": "2026-04-06",
  "공사장덮친건설자재난5월셧다운공포확산건설현장중동발": "2026-04-06",
  "기획오일쇼크집으로짓기도팔기도어렵다": "2026-04-06",
  "생성형AI가구현한아파트의삶GS건설분양마케팅": "2026-04-06",
  "현대건설시공힐스테이트안양펠루스홍보관주말3일간약3000명": "2026-04-06",
  "공사비협상좀PM모시는정비사업장": "2026-04-06",
  "로펌Biz정비사업원스톱팀가동자문분쟁입체지원": "2026-04-06",
  "재생에너지는멀고전기는급하다다시가스발전켜는구글": "2026-04-06",
  "경주시미래에너지허브iSMR유치총력자원봉사자핵심메신저": "2026-04-06",
  "대우건설해외원자력통합조직개편글로벌에너지시장공략": "2026-04-06",
  "스페이스X오픈AI등5개헥토콘연내IPO합산가치5500조": "2026-04-06",
  "조흥수대한전문건설협회인천시회장인천건설산업구조적위기지": "2026-04-06",
  "SOC건설덮친아스콘쇼크도로포장업7000여곳개점휴업": "2026-04-06",
  "건설사연봉희비GS건설1억돌파포스코대우": "2026-04-06",
  "DL이앤씨압구정5구역설계시공위해글로벌기업과협업": "2026-04-06",
  "DL이앤씨글로벌협업으로압구정5구역초고층기준다시쓴다": "2026-04-06",
  "비즈DL이앤씨압구정5구역에글로벌기술총집결초고층건설새기": "2026-04-06",
  "현대건설플랜트비중30까지확대에너지수주박차": "2026-04-06",
  "중동전쟁석유위기속중국수소엔진화물기첫비행으로": "2026-04-06",
  "포럼ADB가터준소형원자로수출": "2026-04-06",
  "증시전략이란대폭격데드라인임박속물가지표촉각파장은": "2026-04-06",
  "도봉구GTXC공사비갈등해소환영4월말본격공사돌입": "2026-04-06",
  "금통위poll이란전쟁물가에먼저타격전원전망치상향": "2026-04-06"
}